{
"meta":{"test_sets":[],"test_metrics":[],"learn_metrics":[{"best_value":"Min","name":"RMSE"}],"launch_mode":"Train","parameters":"","iteration_count":260,"learn_sets":["learn"],"name":"experiment"},
"iterations":[
{"learn":[1738161.925],"iteration":0,"passed_time":0.02663259146,"remaining_time":6.897841188},
{"learn":[1715667.977],"iteration":1,"passed_time":0.02739244149,"remaining_time":3.533624952},
{"learn":[1701314.35],"iteration":2,"passed_time":0.3147558484,"remaining_time":26.96408435},
{"learn":[1680461.776],"iteration":3,"passed_time":0.3155350045,"remaining_time":20.19424029},
{"learn":[1661083.282],"iteration":4,"passed_time":0.316154215,"remaining_time":16.12386497},
{"learn":[1644952.207],"iteration":5,"passed_time":0.3291789055,"remaining_time":13.93524033},
{"learn":[1626961.672],"iteration":6,"passed_time":0.3357488738,"remaining_time":12.13492358},
{"learn":[1610449.713],"iteration":7,"passed_time":0.3424488862,"remaining_time":10.78713992},
{"learn":[1595118.246],"iteration":8,"passed_time":0.3936757017,"remaining_time":10.9791779},
{"learn":[1578041.016],"iteration":9,"passed_time":0.4003511391,"remaining_time":10.00877848},
{"learn":[1561678.71],"iteration":10,"passed_time":0.406845516,"remaining_time":9.209503044},
{"learn":[1546006.411],"iteration":11,"passed_time":0.4074737888,"remaining_time":8.421124969},
{"learn":[1528056.433],"iteration":12,"passed_time":0.4085146679,"remaining_time":7.76177869},
{"learn":[1516484.844],"iteration":13,"passed_time":0.6908124632,"remaining_time":12.13856185},
{"learn":[1501609.224],"iteration":14,"passed_time":0.6976428706,"remaining_time":11.39483355},
{"learn":[1486467.599],"iteration":15,"passed_time":0.7486906549,"remaining_time":11.41753249},
{"learn":[1469666.24],"iteration":16,"passed_time":0.750553802,"remaining_time":10.72850435},
{"learn":[1453986.82],"iteration":17,"passed_time":0.7523927499,"remaining_time":10.11550253},
{"learn":[1440648.69],"iteration":18,"passed_time":0.758904636,"remaining_time":9.626106173},
{"learn":[1428336.032],"iteration":19,"passed_time":1.042051127,"remaining_time":12.50461352},
{"learn":[1415503.665],"iteration":20,"passed_time":1.093244373,"remaining_time":12.44216215},
{"learn":[1404572.678],"iteration":21,"passed_time":1.375645223,"remaining_time":14.88198014},
{"learn":[1392706.047],"iteration":22,"passed_time":1.376447206,"remaining_time":14.18339077},
{"learn":[1379606.693],"iteration":23,"passed_time":1.378377425,"remaining_time":13.55404468},
{"learn":[1368096.624],"iteration":24,"passed_time":1.381779667,"remaining_time":12.98872887},
{"learn":[1357749.434],"iteration":25,"passed_time":1.663775921,"remaining_time":14.97398329},
{"learn":[1345861.64],"iteration":26,"passed_time":1.665896292,"remaining_time":14.376068},
{"learn":[1334870.536],"iteration":27,"passed_time":1.948106581,"remaining_time":16.14145453},
{"learn":[1324319.638],"iteration":28,"passed_time":1.99884561,"remaining_time":15.92183917},
{"learn":[1314448.109],"iteration":29,"passed_time":2.04898928,"remaining_time":15.70891781},
{"learn":[1303923.358],"iteration":30,"passed_time":2.172965676,"remaining_time":16.05190773},
{"learn":[1293611.654],"iteration":31,"passed_time":2.296933627,"remaining_time":16.36565209},
{"learn":[1283261.044],"iteration":32,"passed_time":2.322013788,"remaining_time":15.9726403},
{"learn":[1272546.304],"iteration":33,"passed_time":2.44299042,"remaining_time":16.23870103},
{"learn":[1263072.893],"iteration":34,"passed_time":2.710431733,"remaining_time":17.424204},
{"learn":[1252908.396],"iteration":35,"passed_time":2.71685585,"remaining_time":16.90488084},
{"learn":[1243098.083],"iteration":36,"passed_time":2.837931296,"remaining_time":17.10428862},
{"learn":[1232892.04],"iteration":37,"passed_time":2.844405942,"remaining_time":16.61731892},
{"learn":[1223194.761],"iteration":38,"passed_time":2.856484024,"remaining_time":16.1867428},
{"learn":[1213360.766],"iteration":39,"passed_time":2.905173302,"remaining_time":15.97845316},
{"learn":[1203075.981],"iteration":40,"passed_time":2.917420622,"remaining_time":15.58329552},
{"learn":[1194168.556],"iteration":41,"passed_time":2.929678998,"remaining_time":15.20642908},
{"learn":[1184634.22],"iteration":42,"passed_time":3.047641508,"remaining_time":15.37995831},
{"learn":[1176612.085],"iteration":43,"passed_time":3.307783396,"remaining_time":16.2382094},
{"learn":[1167637.899],"iteration":44,"passed_time":3.42520073,"remaining_time":16.36484793},
{"learn":[1159744.687],"iteration":45,"passed_time":3.685188236,"remaining_time":17.14413657},
{"learn":[1151620.033],"iteration":46,"passed_time":3.733196229,"remaining_time":16.91852759},
{"learn":[1143919.61],"iteration":47,"passed_time":3.991958094,"remaining_time":17.63114825},
{"learn":[1135496.876],"iteration":48,"passed_time":4.003954614,"remaining_time":17.24151885},
{"learn":[1126914.426],"iteration":49,"passed_time":4.010084049,"remaining_time":16.84235301},
{"learn":[1118253.464],"iteration":50,"passed_time":4.12785035,"remaining_time":16.91609261},
{"learn":[1110446.412],"iteration":51,"passed_time":4.128207573,"remaining_time":16.51283029},
{"learn":[1102018.341],"iteration":52,"passed_time":4.131363014,"remaining_time":16.13570083},
{"learn":[1094469.914],"iteration":53,"passed_time":4.395797874,"remaining_time":16.76915485},
{"learn":[1087169.124],"iteration":54,"passed_time":4.657618767,"remaining_time":17.3602154},
{"learn":[1079569.665],"iteration":55,"passed_time":4.669788329,"remaining_time":17.01137177},
{"learn":[1072226.458],"iteration":56,"passed_time":4.67570272,"remaining_time":16.65206407},
{"learn":[1065107.227],"iteration":57,"passed_time":4.939483652,"remaining_time":17.20302927},
{"learn":[1057980.729],"iteration":58,"passed_time":5.200404704,"remaining_time":17.71663298},
{"learn":[1050780.859],"iteration":59,"passed_time":5.202199359,"remaining_time":17.34066453},
{"learn":[1043739.13],"iteration":60,"passed_time":5.214011257,"remaining_time":17.00964328},
{"learn":[1036937.645],"iteration":61,"passed_time":5.476645844,"remaining_time":17.4899335},
{"learn":[1029725.635],"iteration":62,"passed_time":5.500581726,"remaining_time":17.20023174},
{"learn":[1022499.116],"iteration":63,"passed_time":5.524581832,"remaining_time":16.91903186},
{"learn":[1016002.726],"iteration":64,"passed_time":5.786530805,"remaining_time":17.35959242},
{"learn":[1009558.925],"iteration":65,"passed_time":5.810532723,"remaining_time":17.07944467},
{"learn":[1005144.481],"iteration":66,"passed_time":5.81072767,"remaining_time":16.73836478},
{"learn":[998292.5034],"iteration":67,"passed_time":5.816745043,"remaining_time":16.42375071},
{"learn":[991290.4385],"iteration":68,"passed_time":5.819837681,"remaining_time":16.10998547},
{"learn":[984593.9255],"iteration":69,"passed_time":5.825848917,"remaining_time":15.81301849},
{"learn":[978468.6892],"iteration":70,"passed_time":6.085907132,"remaining_time":16.20051335},
{"learn":[972062.1883],"iteration":71,"passed_time":6.109862035,"remaining_time":15.95352865},
{"learn":[965956.303],"iteration":72,"passed_time":6.374460077,"remaining_time":16.32909636},
{"learn":[959416.7246],"iteration":73,"passed_time":6.638549161,"remaining_time":16.68608303},
{"learn":[953076.8837],"iteration":74,"passed_time":6.64034869,"remaining_time":16.37952677},
{"learn":[947050.0612],"iteration":75,"passed_time":6.643758681,"remaining_time":16.08488944},
{"learn":[941153.6542],"iteration":76,"passed_time":6.645411416,"remaining_time":15.79364012},
{"learn":[935462.9184],"iteration":77,"passed_time":6.902908422,"remaining_time":16.10678632},
{"learn":[929489.3979],"iteration":78,"passed_time":7.164954478,"remaining_time":16.41590836},
{"learn":[923890.5471],"iteration":79,"passed_time":7.417293481,"remaining_time":16.68891033},
{"learn":[918006.715],"iteration":80,"passed_time":7.662159765,"remaining_time":16.93242714},
{"learn":[911701.8442],"iteration":81,"passed_time":7.665654291,"remaining_time":16.64007883},
{"learn":[905781.513],"iteration":82,"passed_time":7.690200759,"remaining_time":16.39958475},
{"learn":[901448.4882],"iteration":83,"passed_time":7.690855431,"remaining_time":16.11417328},
{"learn":[895885.2404],"iteration":84,"passed_time":7.697227998,"remaining_time":15.84723411},
{"learn":[890156.4975],"iteration":85,"passed_time":7.722076498,"remaining_time":15.62373617},
{"learn":[884772.2467],"iteration":86,"passed_time":7.995928556,"remaining_time":15.89994989},
{"learn":[879100.5294],"iteration":87,"passed_time":8.257668735,"remaining_time":16.13998889},
{"learn":[873787.8269],"iteration":88,"passed_time":8.271375233,"remaining_time":15.89219286},
{"learn":[870888.9946],"iteration":89,"passed_time":8.271897655,"remaining_time":15.62469557},
{"learn":[865691.6335],"iteration":90,"passed_time":8.538797032,"remaining_time":15.85776592},
{"learn":[861754.3223],"iteration":91,"passed_time":8.539554011,"remaining_time":15.59396819},
{"learn":[856585.8132],"iteration":92,"passed_time":8.813267627,"remaining_time":15.8259752},
{"learn":[851642.2057],"iteration":93,"passed_time":9.066529412,"remaining_time":16.01110513},
{"learn":[847091.3704],"iteration":94,"passed_time":9.073695396,"remaining_time":15.75957621},
{"learn":[843140.4591],"iteration":95,"passed_time":9.074740859,"remaining_time":15.5026823},
{"learn":[839675.9174],"iteration":96,"passed_time":9.07504722,"remaining_time":15.24982162},
{"learn":[837290.7748],"iteration":97,"passed_time":9.075383469,"remaining_time":15.00216451},
{"learn":[832560.6133],"iteration":98,"passed_time":9.337466864,"remaining_time":15.18517338},
{"learn":[827881.9609],"iteration":99,"passed_time":9.600894669,"remaining_time":15.36143147},
{"learn":[823815.3035],"iteration":100,"passed_time":9.604339271,"remaining_time":15.11970242},
{"learn":[819159.2496],"iteration":101,"passed_time":9.626928632,"remaining_time":14.91230121},
{"learn":[814780.8451],"iteration":102,"passed_time":9.629993621,"remaining_time":14.67872814},
{"learn":[810135.1739],"iteration":103,"passed_time":9.653921311,"remaining_time":14.48088197},
{"learn":[806656.2119],"iteration":104,"passed_time":9.65455623,"remaining_time":14.25196396},
{"learn":[801888.2571],"iteration":105,"passed_time":9.662115262,"remaining_time":14.03741274},
{"learn":[797211.8214],"iteration":106,"passed_time":9.926199382,"remaining_time":14.19353743},
{"learn":[792610.3722],"iteration":107,"passed_time":10.19965815,"remaining_time":14.35507443},
{"learn":[788755.111],"iteration":108,"passed_time":10.20606665,"remaining_time":14.13867949},
{"learn":[785155.0225],"iteration":109,"passed_time":10.2091807,"remaining_time":13.92161005},
{"learn":[781030.0364],"iteration":110,"passed_time":10.21548852,"remaining_time":13.71268279},
{"learn":[778340.0196],"iteration":111,"passed_time":10.21587816,"remaining_time":13.49955329},
{"learn":[775316.9317],"iteration":112,"passed_time":10.21638741,"remaining_time":13.29034468},
{"learn":[770951.7418],"iteration":113,"passed_time":10.47068348,"remaining_time":13.4098227},
{"learn":[766649.4451],"iteration":114,"passed_time":10.735886,"remaining_time":13.53655192},
{"learn":[762423.9155],"iteration":115,"passed_time":10.7842922,"remaining_time":13.38739721},
{"learn":[759340.1302],"iteration":116,"passed_time":10.78532186,"remaining_time":13.18206005},
{"learn":[755306.524],"iteration":117,"passed_time":10.83273647,"remaining_time":13.03600491},
{"learn":[751917.3756],"iteration":118,"passed_time":10.83694385,"remaining_time":12.84041246},
{"learn":[747882.8277],"iteration":119,"passed_time":10.88455149,"remaining_time":12.69864341},
{"learn":[744855.442],"iteration":120,"passed_time":10.88658502,"remaining_time":12.50607701},
{"learn":[741158.6811],"iteration":121,"passed_time":10.91140987,"remaining_time":12.34241444},
{"learn":[738232.8959],"iteration":122,"passed_time":10.91362021,"remaining_time":12.15582089},
{"learn":[735126.4269],"iteration":123,"passed_time":10.91495445,"remaining_time":11.97124037},
{"learn":[732079.1442],"iteration":124,"passed_time":10.92674307,"remaining_time":11.80088251},
{"learn":[728554.5385],"iteration":125,"passed_time":10.95078981,"remaining_time":11.64607805},
{"learn":[724644.5312],"iteration":126,"passed_time":11.20678748,"remaining_time":11.73624201},
{"learn":[721005.7987],"iteration":127,"passed_time":11.25489781,"remaining_time":11.60661337},
{"learn":[717708.8218],"iteration":128,"passed_time":11.2668725,"remaining_time":11.44155269},
{"learn":[713822.259],"iteration":129,"passed_time":11.52793041,"remaining_time":11.52793041},
{"learn":[710730.5614],"iteration":130,"passed_time":11.54059362,"remaining_time":11.36440135},
{"learn":[708993.1383],"iteration":131,"passed_time":11.54100735,"remaining_time":11.19127986},
{"learn":[707723.1393],"iteration":132,"passed_time":11.54118888,"remaining_time":11.02053374},
{"learn":[704036.979],"iteration":133,"passed_time":11.65901266,"remaining_time":10.9629522},
{"learn":[703102.2556],"iteration":134,"passed_time":11.65939443,"remaining_time":10.79573559},
{"learn":[699851.3524],"iteration":135,"passed_time":11.68336007,"remaining_time":10.65247535},
{"learn":[696186.6593],"iteration":136,"passed_time":11.80122274,"remaining_time":10.59525837},
{"learn":[693962.3774],"iteration":137,"passed_time":11.80185671,"remaining_time":10.4335255},
{"learn":[690327.9821],"iteration":138,"passed_time":11.92000989,"remaining_time":10.37641148},
{"learn":[687296.371],"iteration":139,"passed_time":11.94399394,"remaining_time":10.23770909},
{"learn":[685489.2711],"iteration":140,"passed_time":11.94440285,"remaining_time":10.08073716},
{"learn":[681870.3093],"iteration":141,"passed_time":12.20520041,"remaining_time":10.14234964},
{"learn":[678305.419],"iteration":142,"passed_time":12.46617832,"remaining_time":10.19960044},
{"learn":[676600.1141],"iteration":143,"passed_time":12.46666529,"remaining_time":10.04259148},
{"learn":[673382.3267],"iteration":144,"passed_time":12.51466509,"remaining_time":9.925424039},
{"learn":[670054.5194],"iteration":145,"passed_time":12.77551937,"remaining_time":9.975405535},
{"learn":[668251.6811],"iteration":146,"passed_time":12.77672387,"remaining_time":9.821563249},
{"learn":[665825.3539],"iteration":147,"passed_time":12.7800238,"remaining_time":9.671369366},
{"learn":[662516.1402],"iteration":148,"passed_time":13.03596898,"remaining_time":9.711359442},
{"learn":[659002.3771],"iteration":149,"passed_time":13.2860537,"remaining_time":9.743106049},
{"learn":[656555.1836],"iteration":150,"passed_time":13.28956734,"remaining_time":9.59313139},
{"learn":[654736.7923],"iteration":151,"passed_time":13.29019623,"remaining_time":9.443034161},
{"learn":[651348.4325],"iteration":152,"passed_time":13.54239127,"remaining_time":9.47082265},
{"learn":[648153.6979],"iteration":153,"passed_time":13.7905949,"remaining_time":9.492227656},
{"learn":[646788.8028],"iteration":154,"passed_time":13.7910005,"remaining_time":9.342290664},
{"learn":[643471.1498],"iteration":155,"passed_time":14.05791192,"remaining_time":9.37194128},
{"learn":[640548.3423],"iteration":156,"passed_time":14.30797384,"remaining_time":9.386759905},
{"learn":[638053.9999],"iteration":157,"passed_time":14.32036603,"remaining_time":9.244793261},
{"learn":[636248.9157],"iteration":158,"passed_time":14.32200878,"remaining_time":9.09762822},
{"learn":[634320.3445],"iteration":159,"passed_time":14.3279193,"remaining_time":8.954949562},
{"learn":[631070.3152],"iteration":160,"passed_time":14.59103903,"remaining_time":8.97212959},
{"learn":[627779.1711],"iteration":161,"passed_time":14.84720874,"remaining_time":8.981644794},
{"learn":[624684.5503],"iteration":162,"passed_time":15.09471558,"remaining_time":8.982744856},
{"learn":[621423.0039],"iteration":163,"passed_time":15.33985075,"remaining_time":8.979424831},
{"learn":[618414.7117],"iteration":164,"passed_time":15.60038693,"remaining_time":8.982040957},
{"learn":[616014.3611],"iteration":165,"passed_time":15.6064324,"remaining_time":8.837377381},
{"learn":[613019.4372],"iteration":166,"passed_time":15.8599162,"remaining_time":8.832168904},
{"learn":[609928.7077],"iteration":167,"passed_time":16.108389,"remaining_time":8.821260642},
{"learn":[607619.3699],"iteration":168,"passed_time":16.13201842,"remaining_time":8.686471456},
{"learn":[605051.1608],"iteration":169,"passed_time":16.15511071,"remaining_time":8.552705667},
{"learn":[601982.5578],"iteration":170,"passed_time":16.39909115,"remaining_time":8.535199489},
{"learn":[599183.869],"iteration":171,"passed_time":16.65517725,"remaining_time":8.521253476},
{"learn":[598689.4754],"iteration":172,"passed_time":16.6554196,"remaining_time":8.37584685},
{"learn":[596023.8236],"iteration":173,"passed_time":16.70360369,"remaining_time":8.255804123},
{"learn":[593227.4426],"iteration":174,"passed_time":16.82403578,"remaining_time":8.17167452},
{"learn":[590307.6537],"iteration":175,"passed_time":17.08270257,"remaining_time":8.153108046},
{"learn":[587648.1341],"iteration":176,"passed_time":17.20048346,"remaining_time":8.065763431},
{"learn":[585837.6606],"iteration":177,"passed_time":17.20676099,"remaining_time":7.92671012},
{"learn":[583700.8958],"iteration":178,"passed_time":17.21295767,"remaining_time":7.789103749},
{"learn":[582360.7359],"iteration":179,"passed_time":17.21463774,"remaining_time":7.650950108},
{"learn":[579885.7709],"iteration":180,"passed_time":17.26242675,"remaining_time":7.534429357},
{"learn":[577040.1304],"iteration":181,"passed_time":17.52190109,"remaining_time":7.509386184},
{"learn":[576039.7259],"iteration":182,"passed_time":17.52230201,"remaining_time":7.372771883},
{"learn":[573312.0736],"iteration":183,"passed_time":17.787403,"remaining_time":7.346970806},
{"learn":[572449.3507],"iteration":184,"passed_time":17.78777697,"remaining_time":7.211260936},
{"learn":[569614.0719],"iteration":185,"passed_time":18.04893502,"remaining_time":7.180759092},
{"learn":[568695.3389],"iteration":186,"passed_time":18.05009861,"remaining_time":7.046295179},
{"learn":[565781.6287],"iteration":187,"passed_time":18.31022766,"remaining_time":7.012427614},
{"learn":[562986.477],"iteration":188,"passed_time":18.57269566,"remaining_time":6.977044403},
{"learn":[562040.9561],"iteration":189,"passed_time":18.57344892,"remaining_time":6.842849604},
{"learn":[560893.5581],"iteration":190,"passed_time":18.5740676,"remaining_time":6.710003478},
{"learn":[558127.0436],"iteration":191,"passed_time":18.83428598,"remaining_time":6.670476285},
{"learn":[556337.1025],"iteration":192,"passed_time":18.85792597,"remaining_time":6.546533886},
{"learn":[555515.3256],"iteration":193,"passed_time":18.8583868,"remaining_time":6.415739839},
{"learn":[553041.4523],"iteration":194,"passed_time":18.97709086,"remaining_time":6.325696952},
{"learn":[550792.0755],"iteration":195,"passed_time":19.0251137,"remaining_time":6.212282023},
{"learn":[548424.5414],"iteration":196,"passed_time":19.28626117,"remaining_time":6.167687583},
{"learn":[546436.8273],"iteration":197,"passed_time":19.3101372,"remaining_time":6.046608618},
{"learn":[544288.1026],"iteration":198,"passed_time":19.57172477,"remaining_time":5.999372918},
{"learn":[541868.7406],"iteration":199,"passed_time":19.83291765,"remaining_time":5.949875295},
{"learn":[539248.6143],"iteration":200,"passed_time":20.10048094,"remaining_time":5.900141171},
{"learn":[536502.9151],"iteration":201,"passed_time":20.36327954,"remaining_time":5.846882244},
{"learn":[534012.8502],"iteration":202,"passed_time":20.62358628,"remaining_time":5.790859202},
{"learn":[533393.1363],"iteration":203,"passed_time":20.6238717,"remaining_time":5.661454975},
{"learn":[530960.4107],"iteration":204,"passed_time":20.88591239,"remaining_time":5.603537471},
{"learn":[528521.4687],"iteration":205,"passed_time":21.14646534,"remaining_time":5.543248196},
{"learn":[527763.9925],"iteration":206,"passed_time":21.14685131,"remaining_time":5.414411204},
{"learn":[527061.7017],"iteration":207,"passed_time":21.14716945,"remaining_time":5.286792362},
{"learn":[524649.9459],"iteration":208,"passed_time":21.40720041,"remaining_time":5.223766607},
{"learn":[522310.6105],"iteration":209,"passed_time":21.66893351,"remaining_time":5.159269882},
{"learn":[519952.9856],"iteration":210,"passed_time":21.93163796,"remaining_time":5.093129194},
{"learn":[518045.734],"iteration":211,"passed_time":21.97985417,"remaining_time":4.976570755},
{"learn":[515866.4841],"iteration":212,"passed_time":22.24161115,"remaining_time":4.907773353},
{"learn":[515140.6597],"iteration":213,"passed_time":22.24212969,"remaining_time":4.781018532},
{"learn":[512796.2565],"iteration":214,"passed_time":22.50245381,"remaining_time":4.709815914},
{"learn":[510777.1756],"iteration":215,"passed_time":22.55064307,"remaining_time":4.593649515},
{"learn":[510042.9317],"iteration":216,"passed_time":22.5516557,"remaining_time":4.468761268},
{"learn":[507832.3666],"iteration":217,"passed_time":22.67029607,"remaining_time":4.367671721},
{"learn":[505731.998],"iteration":218,"passed_time":22.93194977,"remaining_time":4.293196076},
{"learn":[503634.0216],"iteration":219,"passed_time":23.19315142,"remaining_time":4.216936621},
{"learn":[501206.3204],"iteration":220,"passed_time":23.45821806,"remaining_time":4.13968554},
{"learn":[498875.8562],"iteration":221,"passed_time":23.72132543,"remaining_time":4.060407056},
{"learn":[496374.1974],"iteration":222,"passed_time":23.98970314,"remaining_time":3.980354333},
{"learn":[494589.2622],"iteration":223,"passed_time":24.03886975,"remaining_time":3.863389781},
{"learn":[493651.1966],"iteration":224,"passed_time":24.03988743,"remaining_time":3.739538045},
{"learn":[492332.7047],"iteration":225,"passed_time":24.04612502,"remaining_time":3.617558631},
{"learn":[490065.6844],"iteration":226,"passed_time":24.31116896,"remaining_time":3.5342228},
{"learn":[489626.5974],"iteration":227,"passed_time":24.31148779,"remaining_time":3.412138637},
{"learn":[487523.2035],"iteration":228,"passed_time":24.57743573,"remaining_time":3.327076453},
{"learn":[485569.7486],"iteration":229,"passed_time":24.84121469,"remaining_time":3.240158438},
{"learn":[483133.8008],"iteration":230,"passed_time":25.10413203,"remaining_time":3.15160099},
{"learn":[480953.9967],"iteration":231,"passed_time":25.36783068,"remaining_time":3.061634737},
{"learn":[478854.1781],"iteration":232,"passed_time":25.62582342,"remaining_time":2.969516018},
{"learn":[476792.6767],"iteration":233,"passed_time":25.88126518,"remaining_time":2.875696131},
{"learn":[474881.7584],"iteration":234,"passed_time":26.13446859,"remaining_time":2.780262616},
{"learn":[472659.9176],"iteration":235,"passed_time":26.38601125,"remaining_time":2.683323178},
{"learn":[470524.6595],"iteration":236,"passed_time":26.64051666,"remaining_time":2.585366596},
{"learn":[468741.3821],"iteration":237,"passed_time":26.89991461,"remaining_time":2.486546729},
{"learn":[466616.9684],"iteration":238,"passed_time":27.16021124,"remaining_time":2.386462076},
{"learn":[464550.3027],"iteration":239,"passed_time":27.4191864,"remaining_time":2.2849322},
{"learn":[462538.4304],"iteration":240,"passed_time":27.67169832,"remaining_time":2.181586175},
{"learn":[460617.7705],"iteration":241,"passed_time":27.92862424,"remaining_time":2.077335687},
{"learn":[458663.4461],"iteration":242,"passed_time":28.1954984,"remaining_time":1.972524579},
{"learn":[456751.148],"iteration":243,"passed_time":28.45075784,"remaining_time":1.865623465},
{"learn":[454792.3141],"iteration":244,"passed_time":28.71062739,"remaining_time":1.757793514},
{"learn":[452901.1792],"iteration":245,"passed_time":28.96626344,"remaining_time":1.648486537},
{"learn":[451120.2709],"iteration":246,"passed_time":29.2272138,"remaining_time":1.53827441},
{"learn":[448899.2271],"iteration":247,"passed_time":29.48833501,"remaining_time":1.42685492},
{"learn":[446905.9085],"iteration":248,"passed_time":29.74751504,"remaining_time":1.314147251},
{"learn":[445225.2627],"iteration":249,"passed_time":29.77156674,"remaining_time":1.19086267},
{"learn":[443390.1139],"iteration":250,"passed_time":30.03127696,"remaining_time":1.076818696},
{"learn":[442865.7591],"iteration":251,"passed_time":30.03178696,"remaining_time":0.9533900623},
{"learn":[441077.474],"iteration":252,"passed_time":30.14963299,"remaining_time":0.8341795689},
{"learn":[439430.971],"iteration":253,"passed_time":30.41055318,"remaining_time":0.718359524},
{"learn":[437515.7442],"iteration":254,"passed_time":30.67743546,"remaining_time":0.6015183423},
{"learn":[435769.4656],"iteration":255,"passed_time":30.94353175,"remaining_time":0.4834926836},
{"learn":[433833.4248],"iteration":256,"passed_time":31.18892396,"remaining_time":0.3640730424},
{"learn":[431937.3579],"iteration":257,"passed_time":31.43874973,"remaining_time":0.2437112382},
{"learn":[429962.9746],"iteration":258,"passed_time":31.69555396,"remaining_time":0.1223766562},
{"learn":[429607.8347],"iteration":259,"passed_time":31.69589012,"remaining_time":0}
]}